phylotrackpy-0.2.4.dist-info/RECORD
phylotrackpy-0.2.4.dist-info/LICENSE
phylotrackpy-0.2.4.dist-info/WHEEL
phylotrackpy-0.2.4.dist-info/top_level.txt
phylotrackpy-0.2.4.dist-info/METADATA
phylotrackpy/__init__.py
phylotrackpy/systematics.cpython-312-darwin.so
