Metadata-Version: 2.1
Name: phylotrackpy
Version: 0.2.4
Summary: A python phylogeny tracking module
Home-page: https://github.com/emilydolson/python-phylogeny-tracker
Author: Emily Dolson
Author-email: emilyldolson@gmail.com
Requires-Python: >=3.7
License-File: LICENSE
Provides-Extra: test
Requires-Dist: pytest; extra == "test"
